indicators/CCI.py
indicators/DMI.py
indicators/MACD.py
indicators/RSI.py
indicators/__init__.py
indicators/moving_average.py
indicators/stoch.py
TradingView_Indicators-1.0.0.dist-info/METADATA
TradingView_Indicators-1.0.0.dist-info/WHEEL
TradingView_Indicators-1.0.0.dist-info/top_level.txt
TradingView_Indicators-1.0.0.dist-info/RECORD
