Metadata-Version: 2.1
Name: TradingView-Indicators
Version: 1.0.0
Summary: An accurate calculation of technical analysis indicators
Author: m-marqx (Mateus Marques)
Keywords: python,TradingView,technical analysis,indicators
Classifier: Development Status :: 1 - Planning
Classifier: Intended Audience :: Developers
Classifier: Programming Language :: Python :: 3
Classifier: Operating System :: Unix
Classifier: Operating System :: MacOS :: MacOS X
Classifier: Operating System :: Microsoft :: Windows
Requires-Dist: pandas
Requires-Dist: numpy
